<?xml version="1.0" encoding="utf-8"?>
<!DOCTYPE hibernate-mapping PUBLIC "-//Hibernate/Hibernate Mapping DTD 3.0//EN"
"http://hibernate.sourceforge.net/hibernate-mapping-3.0.dtd">
<!-- 
    Mapping file autogenerated by MyEclipse Persistence Tools
-->
<hibernate-mapping>
    <class name="com.rimi.ctibet.domain.View" table="tview">
        <id name="id" column="id">
            <generator class="native"/>
        </id>
        <property name="code" column="code" type="java.lang.String"/>
        
        <property name="viewName"         column="viewName"        type="java.lang.String"/>
        <property name="destinationCode"  column="destinationCode" type="java.lang.String"/>
        <property name="goneCount"        column="goneCount"/>
        <property name="wantCount"        column="wantCount"/>
        <property name="fakeGoneCount"    column="fakeGoneCount"/>
        <property name="fakeWantCount"    column="fakeWantCount"/>
        <property name="img"        	  column="img"       	   type="java.lang.String"/>
        <property name="viewImage"        column="viewImage"       type="java.lang.String"/>
        <property name="view_360full"     column="view_360full"    type="java.lang.String"/>
        <property name="viewIntroduce"    column="viewIntroduce"   type="java.lang.String"/>
        <property name="ticketPrice"      column="ticketPrice"     type="java.lang.String"/>
        <property name="ticketUrl"        column="ticketUrl"       type="java.lang.String"/>
        <property name="isHaveGateTicket" column="isHaveGateTicket"/>
        <property name="checkNum" 		  column="checkNum"/>
        <property name="fakeCheckNum" 	  column="fakeCheckNum"/>
        <property name="replyNum"         column="replyNum"/>
        <property name="likeNum"          column="likeNum"/>
        <property name="fakeLikeNum"      column="fakeLikeNum"/>
        
        <property name="guide"            column="guide"/>
        <property name="traffic"      	  column="traffic"/>
        <property name="notice"      	  column="notice"/>
        <property name="shortGuide"       column="shortGuide"/>
        <property name="shortTraffic"     column="shortTraffic"/>
        <property name="shortNotice"      column="shortNotice"/>
        
        <property name="address"      	  column="address"/>
        <property name="hdFullUrl"        column="hdFullUrl"/>
        <property name="realSceneVideoUrl" column="realSceneVideoUrl"/>
        <property name="xy" column="xy"/>

        <property name="linkUrl" column="linkUrl"/>
        <property name="keyword" column="keyword"/>
       	
        <property name="tdkTitle"       column="tdkTitle"/>
      	<property name="tdkDescription" column="tdkDescription"/>
        <property name="tdkKeywords"    column="tdkKeywords"/>
        
        <property name="createTime"   column="createTime"   type="java.util.Date" update="false"/>
        <property name="lastEditTime" column="lastEditTime" type="java.util.Date"/>
        <property name="avaliable"    column="avaliable"/>
    </class>
</hibernate-mapping>
